matsim/Events.py
matsim/Facility.py
matsim/Household.py
matsim/Network.py
matsim/Plans.py
matsim/TripEventHandler.py
matsim/Vehicle.py
matsim/__init__.py
matsim/utils.py
matsim/writers.py
matsim/calibration/__init__.py
matsim/calibration/__main__.py
matsim/calibration/analysis.py
matsim/calibration/base.py
matsim/calibration/calib_asc.py
matsim/calibration/calib_asc_dist.py
matsim/calibration/calib_dist.py
matsim/calibration/calib_group_asc.py
matsim/calibration/constraints.py
matsim/calibration/plot.py
matsim/calibration/run_create_csv.py
matsim/calibration/run_simulations.py
matsim/calibration/utils.py
matsim/cli/__init__.py
matsim/cli/clean_iters.py
matsim/cli/main.py
matsim/pb/Events_pb2.py
matsim/pb/Ids_pb2.py
matsim/pb/Model_pb2.py
matsim/pb/Wireformat_pb2.py
matsim/pb/__init__.py
matsim/scenariogen/__init__.py
matsim/scenariogen/__main__.py
matsim/scenariogen/freight.py
matsim/scenariogen/data/__init__.py
matsim/scenariogen/data/preparation.py
matsim/scenariogen/data/run_create_ref_data.py
matsim/scenariogen/data/run_extract_activities.py
matsim/scenariogen/data/run_lookup_regiostar.py
matsim/scenariogen/data/formats/__init__.py
matsim/scenariogen/data/formats/jp_milt.py
matsim/scenariogen/data/formats/mid.py
matsim/scenariogen/data/formats/netcheck.py
matsim/scenariogen/data/formats/srv.py
matsim/scenariogen/facilities/__init__.py
matsim/scenariogen/ml/__init__.py
matsim/scenariogen/ml/models.py
matsim/scenariogen/ml/models_feyn.py
matsim/scenariogen/ml/train.py
matsim/scenariogen/network/__init__.py
matsim/scenariogen/network/features.py
matsim/scenariogen/network/models.py
matsim/scenariogen/network/models_feyn.py
matsim/scenariogen/network/randomTrips.py
matsim/scenariogen/network/run_collect_results.py
matsim/scenariogen/network/run_edges.py
matsim/scenariogen/network/run_intersections.py
matsim/scenariogen/network/run_opt_freespeed.py
matsim/scenariogen/network/run_routes.py
matsim/scenariogen/network/run_train_model.py
matsim_tools-0.0.21.dist-info/METADATA
matsim_tools-0.0.21.dist-info/WHEEL
matsim_tools-0.0.21.dist-info/entry_points.txt
matsim_tools-0.0.21.dist-info/top_level.txt
matsim_tools-0.0.21.dist-info/RECORD
