Metadata-Version: 2.1
Name: matsim-tools
Version: 0.0.21
Summary: MATSim Agent-Based Transportation Simulation Framework - official python tools
Home-page: https://github.com/matsim-vsp/matsim-python-tools
Author: VSP-Berlin
Author-email: charlton@tu-berlin.de
License: GPLv3
Classifier: License :: OSI Approved :: GNU General Public License (GPL)
Classifier: Programming Language :: Python :: 3
Requires-Dist: protobuf (>=3.20.0)
Requires-Dist: xopen (>=1.7.0)
Requires-Dist: pandas (>=2.1.0)
Provides-Extra: calibration
Requires-Dist: optuna (>=3.3.0) ; extra == 'calibration'
Requires-Dist: shapely (>=1.8.0) ; extra == 'calibration'
Requires-Dist: geopandas (>=1.0.0) ; extra == 'calibration'
Requires-Dist: scikit-learn ; extra == 'calibration'
Provides-Extra: scenariogen
Requires-Dist: sumolib ; extra == 'scenariogen'
Requires-Dist: traci ; extra == 'scenariogen'
Requires-Dist: lxml ; extra == 'scenariogen'
Requires-Dist: optax ; extra == 'scenariogen'
Requires-Dist: requests ; extra == 'scenariogen'
Requires-Dist: tqdm ; extra == 'scenariogen'
Requires-Dist: scikit-learn ; extra == 'scenariogen'
Requires-Dist: xgboost (==1.7.1) ; extra == 'scenariogen'
Requires-Dist: lightgbm ; extra == 'scenariogen'
Requires-Dist: sklearn-contrib-lightning ; extra == 'scenariogen'
Requires-Dist: numpy ; extra == 'scenariogen'
Requires-Dist: sympy ; extra == 'scenariogen'
Requires-Dist: m2cgen ; extra == 'scenariogen'
Requires-Dist: shapely ; extra == 'scenariogen'
Requires-Dist: optuna ; extra == 'scenariogen'
Requires-Dist: statsmodels ; extra == 'scenariogen'
Provides-Extra: viz
Requires-Dist: dash ; extra == 'viz'
Requires-Dist: plotly.express ; extra == 'viz'
Requires-Dist: dash-cytoscape ; extra == 'viz'
Requires-Dist: dash-bootstrap-components ; extra == 'viz'
